dfmpy/__init__.py
dfmpy/__main__.py
dfmpy/commands/__init__.py
dfmpy/commands/add.py
dfmpy/commands/initialize.py
dfmpy/commands/ls.py
dfmpy/commands/sync.py
dfmpy/commands/uninstall.py
dfmpy/files/__init__.py
dfmpy/files/constants.py
dfmpy/files/deleter.py
dfmpy/files/finder.py
dfmpy/files/normalizer.py
dfmpy/files/syncer.py
dfmpy/resources/__init__.py
dfmpy/resources/config.ini
dfmpy/resources/config.py
dfmpy/resources/ignore.globs
dfmpy/utils/__init__.py
dfmpy/utils/interactive.py
dfmpy/utils/logging.py
dfmpy-1.0.0.dist-info/LICENSE.md
dfmpy-1.0.0.dist-info/METADATA
dfmpy-1.0.0.dist-info/WHEEL
dfmpy-1.0.0.dist-info/entry_points.txt
dfmpy-1.0.0.dist-info/top_level.txt
dfmpy-1.0.0.dist-info/RECORD
